LICENSE.txt
MANIFEST.in
setup.py
libs/pylodsc/include/Dictionary.h
libs/pylodsc/include/PyDictionary.h
libs/pylodsc/include/pylodsc.h
libs/pylodsc/include/pylodscapi.h
libs/pylodsc/src/Dictionary.cpp
pylods_msgpack.egg-info/PKG-INFO
pylods_msgpack.egg-info/SOURCES.txt
pylods_msgpack.egg-info/dependency_links.txt
pylods_msgpack.egg-info/requires.txt
pylods_msgpack.egg-info/top_level.txt
pylodsmsgpack/__init__.py
pylodsmsgpack/pylodsmsgpack.py
pylodsmsgpackc/include/MsgpackDictionary.h
pylodsmsgpackc/src/MsgpackDictionary.cpp
pylodsmsgpackc/src/pylodsmsgpackcapi.cpp