Metadata-Version: 1.1
Name: pylods-msgpack
Version: 0.3.7
Summary: Msgpack extension for pylods package
Home-page: https://github.com/salimm/pylods-msgpack
Author: Salim Malakouti
Author-email: salim.malakouti@gmail.com
License: MIT
Download-URL: http://github.com/salimm/pylods-msgpack/archive/0.3.7.tar.gz
Keywords: python,serialization,deserialization,parser,json,object oriented,fast,extendable,type based,jackson json,msgpack,umsgpack
Platform: UNKNOWN
Classifier: Programming Language :: Python
